setup.py
pyagentx/__init__.py
pyagentx/agent.py
pyagentx/network.py
pyagentx/pdu.py
pyagentx/updater.py
pyagentx.egg-info/PKG-INFO
pyagentx.egg-info/SOURCES.txt
pyagentx.egg-info/dependency_links.txt
pyagentx.egg-info/top_level.txt