Metadata-Version: 1.0
Name: pyagentx
Version: 0.2
Summary: AgentX package to extend SNMP with pure Python
Home-page: https://github.com/rayed/pyagentx
Author: Rayed Alrashed
Author-email: rayed@rayed.com
License: BSD
Keywords: snmp network agentx
Platform: UNKNOWN
Classifier: Development Status :: 4 - Beta
Classifier: License :: OSI Approved :: BSD License
Classifier: Environment :: No Input/Output (Daemon)
Classifier: Topic :: System :: Monitoring
Classifier: Topic :: System :: Networking
Classifier: Programming Language :: Python
Classifier: Intended Audience :: Developers
Classifier: Intended Audience :: Information Technology
Classifier: Intended Audience :: System Administrators
Classifier: Intended Audience :: Telecommunications Industry
